tests/__init__.py
py_mod_test-1.0.11.dist-info/METADATA
py_mod_test-1.0.11.dist-info/WHEEL
py_mod_test-1.0.11.dist-info/top_level.txt
py_mod_test-1.0.11.dist-info/RECORD
